{
"chasseurs": [
        {
            "id": 1,
            "nom": "Aiden",
            "rang_de_chasseur": 86,
            "specialisation": "Épéiste",
            "armeEquipee": 1,
            "monstresFavoris": [
                1,
                3
            ],
            "notes": 4.5,
            "setArmureEquipee": 1
        },
        {
            "id": 2,
            "nom": "Lyra",
            "rang_de_chasseur": 12,
            "specialisation": "Artilleur",
            "armeEquipee": 2,
            "monstresFavoris": [
                2
            ],
            "notes": 3.8,
            "setArmureEquipee": 4
        },
        {
            "id": 3,
            "nom": "Hanz",
            "rang_de_chasseur": 45,
            "specialisation": "Épéiste",
            "armeEquipee": 3,
            "monstresFavoris": [
                3,
                4
            ],
            "notes": 5,
            "setArmureEquipee": 3
        },{
            "id": 4,
            "nom": "Zara",
            "rang_de_chasseur": 67,
            "specialisation": "Maître d'armes",
            "armeEquipee": 4,
            "monstresFavoris": [
                5,
                6
            ],
            "notes": 4.7,
            "setArmureEquipee": 5
        },
        {
            "id": 5,
            "nom": "Kenji",
            "rang_de_chasseur": 92,
            "specialisation": "Artilleur",
            "armeEquipee": 5,
            "monstresFavoris": [
                7,
                8
            ],
            "notes": 4.9,
            "setArmureEquipee": 6
        },
        {
            "id": 6,
            "nom": "Sasha",
            "rang_de_chasseur": 23,
            "specialisation": "Maître d'armes",
            "armeEquipee": 6,
            "monstresFavoris": [
                9,
                10
            ],
            "notes": 4.6,
            "setArmureEquipee": 7
        },
                {
            "id": 7,
            "nom": "Drake",
            "rang_de_chasseur": 78,
            "specialisation": "Épéiste",
            "armeEquipee": 7,
            "monstresFavoris": [
                11,
                12
            ],
            "notes": 4.8,
            "setArmureEquipee": 8
        },
        {
            "id": 8,
            "nom": "Rina",
            "rang_de_chasseur": 55,
            "specialisation": "Artilleur",
            "armeEquipee": 8,
            "monstresFavoris": [
                13,
                14
            ],
            "notes": 4.5,
            "setArmureEquipee": 1
        }
    ],
    "armes": [
        {
            "id": 1,
            "nom": "Lame Wyvern \"Érable\"",
            "type": "Grande épée",
            "attaque": 120,
            "element": "Feu"
        },
        {
            "id": 2,
            "nom": "Arc de chasseur II",
            "type": "Arc",
            "attaque": 80,
            "element": null
        },
        {
            "id": 3,
            "nom": "Destruction du Nergigante",
            "type": "Epée longue",
            "attaque": 180,
            "element": "Dragon"
        },
        {
            "id": 4,
            "nom": "Marteau de guerre",
            "type": "Marteau",
            "attaque": 150,
            "element": "Explosion"
        },
        {
            "id": 5,
            "nom": "Fusarbalète lourde X",
            "type": "Fusarbalète lourde",
            "attaque": 110,
            "element": null
        },
        {
            "id": 6,
            "nom": "Volto-hache royale",
            "type": "Volto-hache",
            "attaque": 160,
            "element": "Foudre"
        },
        {
            "id": 7,
            "nom": "Lame démoniaque",
            "type": "Double lames",
            "attaque": 140,
            "element": "Dragon"
        },
        {
            "id": 8,
            "nom": "Cor de chasse mélodique",
            "type": "Cor de chasse",
            "attaque": 130,
            "element": "Glace"
        }
    ],
    "monstres": [
        {
            "id": 1,
            "nom": "Rathalos",
            "img": "MHW-Rathalos_Icon.png",
            "type_id": [
                7
            ],
            "environnement_id": [
                1
            ],
            "faiblesses": [
                "Eau",
                "Glace"
            ],
            "materiaux": [
                "Écailles de Rathalos",
                "Griffes de Rathalos",
                "Ailes de Rathalos",
                "Queue de Rathalos",
                "Rubis de Rathalos"
            ],
            "notes": 4.2
        },
        {
            "id": 2,
            "nom": "Khezu",
            "img": "MHRise-Khezu_Icon.png",
            "type_id": [
                3
            ],
            "environnement_id": [
                2
            ],
            "faiblesses": [
                "Foudre",
                "Glace"
            ],
            "materiaux": [
                "Peau de Khezu",
                "Cerveau de Khezu",
                "Queue de Khezu",
                "Os de Khezu",
                "Ampoule pâle"
            ],
            "notes": 4.8
        },
        {
            "id": 3,
            "nom": "Tigrex",
            "img": "MHWI-Tigrex_Icon.png",
            "type_id": [
                6
            ],
            "environnement_id": [
                1
            ],
            "faiblesses": [
                "Glace",
                "Eau"
            ],
            "materiaux": [
                "Griffes de Tigrex",
                "Peau de Tigrex",
                "Queue de Tigrex",
                "Mâchoire de Tigrex",
                "Écaille de Tigrex"
            ],
            "notes": 4.9
        },
        {
            "id": 4,
            "nom": "Zinogre",
            "img": "MHWI-Zinogre_Icon.png",
            "type_id": [
                7
            ],
            "environnement_id": [
                2
            ],
            "faiblesses": [
                "Glace",
                "Eau"
            ],
            "materiaux": [
                "Écaille de Zinogre",
                "Corne de Zinogre",
                "Queue de Zinogre",
                "Griffe de Zinogre",
                "Gemme de Zinogre"
            ],
            "notes": 4.9
        },
        {
            "id": 5,
            "nom": "Brachydios",
            "img": "MHWI-Brachydios_Icon.png",
            "type_id": [
                2
            ],
            "environnement_id": [
                2
            ],
            "faiblesses": [
                "Eau",
                "Glace"
            ],
            "materiaux": [
                "Peau de Brachydios",
                "Sphères de Brachydios",
                "Queue de Brachydios",
                "Masse de Brachydios",
                "Fluide explosif"
            ],
            "notes": 4.5
        },
        {
            "id": 6,
            "nom": "Nargacuga",
            "img": "MHWI-Nargacuga_Icon.png",
            "type_id": [
                6
            ],
            "environnement_id": [
                1
            ],
            "faiblesses": [
                "Foudre",
                "Eau"
            ],
            "materiaux": [
                "Ailes de Nargacuga",
                "Griffes de Nargacuga",
                "Queue de Nargacuga",
                "Écaille de Nargacuga",
                "Médulle de Nargacuga"
            ],
            "notes": 4.6
        },
        {
            "id": 7,
            "nom": "Zorah Magdaros",
            "img": "MHW-Legiana_Icon.png",
            "type_id": [
                3
            ],
            "environnement_id": [
                2
            ],
            "faiblesses": [
                "Eau",
                "Glace"
            ],
            "materiaux": [
                "Écailles de Zorah Magdaros",
                "Flammes de Zorah Magdaros",
                "Magma de Zorah Magdaros",
                "Carapace de Zorah Magdaros",
                "Coeur de Zorah Magdaros"
            ],
            "notes": 4.7
        },
        {
            "id": 8,
            "nom": "Legiana",
            "img": "MHW-Legiana_Icon.png",
            "type_id": [
                4
            ],
            "environnement_id": [
                3
            ],
            "faiblesses": [
                "Feu",
                "Foudre"
            ],
            "materiaux": [
                "Ailes de Legiana",
                "Peau de Legiana",
                "Queue de Legiana",
                "Griffe de Legiana",
                "Cristal de Legiana"
            ],
            "notes": 4.4
        },
        {
            "id": 9,
            "nom": "Diablos",
            "img": "MHW-Diablos_Icon.png",
            "type_id": [
                10
            ],
            "environnement_id": [
                4
            ],
            "faiblesses": [
                "Eau",
                "Glace"
            ],
            "materiaux": [
                "Cornes de Diablos",
                "Peau de Diablos",
                "Queue de Diablos",
                "Carapace de Diablos",
                "Écaille de Diablos"
            ],
            "notes": 4.8
        },
        {
            "id": 10,
            "nom": "Nergigante",
            "img": "MHW-Nergigante_Icon.png",
            "type_id": [
                12
            ],
            "environnement_id": [
                2
            ],
            "faiblesses": [
                "Glace",
                "Eau"
            ],
            "materiaux": [
                "Cornes de Nergigante",
                "Regeneration de Nergigante",
                "Écaille de Nergigante",
                "Queue de Nergigante",
                "Griffe de Nergigante"
            ],
            "notes": 4.9
        },
        {
            "id": 11,
            "nom": "Lunastra",
            "img": "MHW-Lunastra_Icon.png",
            "type_id": [
                7
            ],
            "environnement_id": [
                1
            ],
            "faiblesses": [
                "Eau",
                "Glace"
            ],
            "materiaux": [
                "Écailles de Lunastra",
                "Flammes de Lunastra",
                "Crinière de Lunastra",
                "Queue de Lunastra",
                "Gemme de Lunastra"
            ],
            "notes": 4.8
        },
        {
            "id": 12,
            "nom": "Vaal Hazak",
            "img": "MHW-Rathalos_Icon.png",
            "type_id": [
                3
            ],
            "environnement_id": [
                5
            ],
            "faiblesses": [
                "Eau",
                "Glace"
            ],
            "materiaux": [
                "Peau de Vaal Hazak",
                "Crocs de Vaal Hazak",
                "Queue de Vaal Hazak",
                "Griffe de Vaal Hazak",
                "Membrane de Vaal Hazak"
            ],
            "notes": 4.6
        },
        {
            "id": 13,
            "nom": "Kushala Daora",
            "type_id": [
                3
            ],
            "environnement_id": [
                6
            ],
            "faiblesses": [
                "Feu",
                "Foudre"
            ],
            "materiaux": [
                "Écailles de Kushala Daora",
                "Griffes de Kushala Daora",
                "Queue de Kushala Daora",
                "Corne de Kushala Daora",
                "Gemme de Kushala Daora"
            ],
            "notes": 4.5
        },
        {
            "id": 14,
            "nom": "Teostra",
            "img": "MHW-Rathalos_Icon.png",
            "type_id": [
                12
            ],
            "environnement_id": [
                1
            ],
            "faiblesses": [
                "Eau",
                "Glace"
            ],
            "materiaux": [
                "Flammes de Teostra",
                "Écailles de Teostra",
                "Crinière de Teostra",
                "Queue de Teostra",
                "Gemme de Teostra"
            ],
            "notes": 4.7
        }
    ],
    "environnements": [
        {
            "id": 1,
            "nom": "Forêt et marais",
            "zones": [
                "zone_1",
                "zone_2"
            ],
            "habitats": [
                "plaine",
                "forêt dense"
            ]
        },
        {
            "id": 2,
            "nom": "Volcan",
            "zones": [
                "zone_1",
                "zone_2"
            ],
            "habitats": [
                "sol rocheux",
                "lave"
            ]
        },
        {
            "id": 3,
            "nom": "Prairies glacées",
            "zones": [
                "zone_1",
                "zone_2"
            ],
            "habitats": [
                "neige",
                "glaciers"
            ]
        },
        {
            "id": 4,
            "nom": "Désert",
            "zones": [
                "zone_1",
                "zone_2"
            ],
            "habitats": [
                "sable",
                "ruines"
            ]
        },
        {
            "id": 5,
            "nom": "Cavernes souterraines",
            "zones": [
                "zone_1",
                "zone_2"
            ],
            "habitats": [
                "obscurité",
                "mines"
            ]
        },
        {
            "id": 6,
            "nom": "Plaines sèches",
            "zones": [
                "zone_1",
                "zone_2"
            ],
            "habitats": [
                "savanes",
                "prairies ouvertes"
            ]
        },
        {
            "id": 7,
            "nom": "Îles tropicales",
            "zones": [
                "zone_1",
                "zone_2"
            ],
            "habitats": [
                "plages",
                "forêts humides"
            ]
        }
    ],
    "types_de_monstres": [
        {
            "id": 1,
            "nom": "Bêtes à crocs"
        },
        {
            "id": 2,
            "nom": "Léviathan"
        },
        {
            "id": 3,
            "nom": "Dragon ancien"
        },
        {
            "id": 4,
            "nom": "Aérien"
        },
        {
            "id": 5,
            "nom": "Insectes"
        },
        {
            "id": 6,
            "nom": "Fauves"
        },
        {
            "id": 7,
            "nom": "Wyverns"
        },
        {
            "id": 8,
            "nom": "Poissons"
        },
        {
            "id": 9,
            "nom": "Amphibiens"
        },
        {
            "id": 10,
            "nom": "Reptiles"
        },
        {
            "id": 11,
            "nom": "Golem"
        },
        {
            "id": 12,
            "nom": "Dragons élémentaires"
        },
        {
            "id": 13,
            "nom": "Volants"
        },
        {
            "id": 14,
            "nom": "Céphalopodes"
        },
        {
            "id": 15,
            "nom": "Chimères"
        },
        {
            "id": 16,
            "nom": "Géants"
        }
    ],
    "sets_d_armures": [
        {
            "id": 1,
            "nom": "Armure du Rathalos",
            "monstre_id": 1,
            "composants": [
                {
                    "partie": "Queue de Rathalos",
                    "quantité": 2
                },
                {
                    "partie": "Ailes de Rathalos",
                    "quantité": 3
                },
                {
                    "partie": "Écailles de Rathalos",
                    "quantité": 5
                }
            ],
            "bonus": "Puissance de feu améliorée"
        },
        {
            "id": 2,
            "nom": "Armure du Khezu",
            "monstre_id": 2,
            "composants": [
                {
                    "partie": "Peau de Khezu",
                    "quantité": 6
                },
                {
                    "partie": "Cerveau de Khezu",
                    "quantité": 2
                },
                {
                    "partie": "Os de Khezu",
                    "quantité": 4
                }
            ],
            "bonus": "Augmentation de la défense"
        },
        {
            "id": 3,
            "nom": "Armure du Tigrex",
            "monstre_id": 3,
            "composants": [
                {
                    "partie": "Griffes de Tigrex",
                    "quantité": 4
                },
                {
                    "partie": "Queue de Tigrex",
                    "quantité": 3
                },
                {
                    "partie": "Peau de Tigrex",
                    "quantité": 5
                }
            ],
            "bonus": "Augmentation de la vitesse d'attaque"
        },
        {
            "id": 4,
            "nom": "Armure de Zinogre",
            "monstre_id": 4,
            "composants": [
                {
                    "partie": "Écailles de Zinogre",
                    "quantité": 4
                },
                {
                    "partie": "Ailes de Zinogre",
                    "quantité": 3
                },
                {
                    "partie": "Queue de Zinogre",
                    "quantité": 2
                }
            ],
            "bonus": "Maîtrise de la foudre"
        },
        {
            "id": 5,
            "nom": "Armure du Brachydios",
            "monstre_id": 5,
            "composants": [
                {
                    "partie": "Peau de Brachydios",
                    "quantité": 5
                },
                {
                    "partie": "Queue de Brachydios",
                    "quantité": 3
                },
                {
                    "partie": "Sphères de Brachydios",
                    "quantité": 4
                }
            ],
            "bonus": "Résistance à l'explosion"
        },
        {
            "id": 6,
            "nom": "Armure du Nargacuga",
            "monstre_id": 6,
            "composants": [
                {
                    "partie": "Ailes de Nargacuga",
                    "quantité": 4
                },
                {
                    "partie": "Queue de Nargacuga",
                    "quantité": 2
                },
                {
                    "partie": "Griffes de Nargacuga",
                    "quantité": 5
                }
            ],
            "bonus": "Vitesse d'esquive augmentée"
        },
        {
            "id": 7,
            "nom": "Armure de Diablos",
            "monstre_id": 9,
            "composants": [
                {
                    "partie": "Corne de Diablos",
                    "quantité": 5
                },
                {
                    "partie": "Queue de Diablos",
                    "quantité": 3
                },
                {
                    "partie": "Peau de Diablos",
                    "quantité": 6
                }
            ],
            "bonus": "Augmentation de la défense"
        },
        {
            "id": 8,
            "nom": "Armure de Teostra",
            "monstre_id": 14,
            "composants": [
                {
                    "partie": "Flammes de Teostra",
                    "quantité": 6
                },
                {
                    "partie": "Queue de Teostra",
                    "quantité": 3
                },
                {
                    "partie": "Écailles de Teostra",
                    "quantité": 5
                }
            ],
            "bonus": "Puissance de feu accrue"
        }
    ]
}